Topsis_Arnav_102003760/__init__.py
Topsis_Arnav_102003760/topsis.py
Topsis_Arnav_102003760-1.1.0.dist-info/LICENSE
Topsis_Arnav_102003760-1.1.0.dist-info/METADATA
Topsis_Arnav_102003760-1.1.0.dist-info/WHEEL
Topsis_Arnav_102003760-1.1.0.dist-info/top_level.txt
Topsis_Arnav_102003760-1.1.0.dist-info/RECORD
