Metadata-Version: 2.1
Name: Topsis-Arnav-102003760
Version: 1.1.0
Summary: It evaluates alternatives based on multiple criteria using TOPSIS method
Author: Arnav Goyal
Author-email: <agoyal_be20@thapar.edu>
Classifier: Programming Language :: Python :: 3
Classifier: Operating System :: Unix
Classifier: Operating System :: MacOS :: MacOS X
Classifier: Operating System :: Microsoft :: Windows
License-File: LICENSE
